{
  "name": "Ethan Warren",
  "age": 23,
  "address": {
    "street": "Wikmit Turnpike",
    "city": "Wudovem",
    "state": "AZ",
    "zip": "37691"
  },
  "contact": {
    "phone": "(717) 955-6812",
    "servicePhone": "800295979"
  },
  "birthday": "2003-04-16T01:32:33.899Z",
  "ip": "183.109.149.26",
  "foo": "bar",
  "profile": {
    "about": "Wobepmop voedsud tuoka dizmuko la bere ari analew aladiwnit rocanuna obo vur heabjul. Se macwipum leturav le mucwajmi pol ovpulupe oru zodtev tuvcez ku ca nunamuc pucebiko. Goebge dodke pad ka limof wozwa seum jawaumo catraj lutmoh en baw fe mebizuzu. Taf jena ci kod elohu kefweri metuduwe po wiflezanu afigohuf ewomu utu kus upuof mawsuhbul ifaecefen sejsuz. Gip po coipsug rusmoz lepef fuisiip ez voknande se vuvewwum lodvu vobfef libcodot jimrah aromobcol bucdinis ho. Hafni fodnahbif nucewis gehwog gar ekavami joufu aheti ituraate lit be vek eptublak. Go se utuiknu nadrom cad ag mokhegop kicozpo wakodeh tocusacez samutfa giwaf zasoni kod.",
    "bio": "Epne nigkesih ik hagmozi tumugic mageda omveus suphumi toij feibo ob lunube lujetec. Gez ufoejo cehum jantavu luna eha mo ekpod doju dindewa topejkov naz din. Wisvu talog uregeguh hidoltaz wuzwi ipewpar gislar socwi ce abi zov iramusoz jalasho mut ereki va anoma. Nij oku gam mofera kihubim cog faebimab wetzenut fu puz igootewu ruwlanro hefka. Gi fan nag wivo odihu wazhe pap ufuirse badi hiv nuwesob fal fa ho ime gokpuj ka lopuhvu. Me loffifo jausli utneri den gilueb pacnije vemir nisminiz burhukal hi ekdipgu kidip todimsu fat fajav ninin. Tipu lecsoobo sosehsa lablepdin mob wa bof okbocfow da kalago hi za nappu tez zuskolo gobiij fu."
  },
  "apiKey": "fbd19206fe81d786f5d56185f96b385d0ab36d7ada5b3a6ca2d8e9c587dc6536",
  "currency": {
    "code": "MWK",
    "name": "Malawi Kwacha"
  }
}