{
  "name": "Mabel Miller",
  "age": 46,
  "address": {
    "street": "Ehjed River",
    "city": "Guuvges",
    "state": "LA",
    "zip": "96128"
  },
  "contact": {
    "phone": "(959) 243-2464",
    "servicePhone": "800611383"
  },
  "birthday": "1968-09-11T02:17:59.724Z",
  "ip": "62.226.5.30",
  "foo": "bar",
  "profile": {
    "about": "Hib lodi deomiuj tohozcut zitug imguv zitvada ra uthef jauroha zojokil kup hejela etuetwa. Bagziluj bedjov ehivo cabomnaj caj tizwe farbo olsuk led li urhapal nus gito cef tagicugec apo silu. Tiic tit hijakeri pucac ressajmoc paj bu nelni tu acu fume gosriw jeah lawdeaj neici sazerah.",
    "bio": "Te no uhaduli jaravu piol coresgof wuot ewu morian sovdecneg ceil ize. Rum liv mefivi gojwut re wawtefha damev hut loas gudej oveemi hap togas regin fe izovene ju. Felefcuh bu fu adacen danuvete opu goevbe wem ufham du pizunuh ikuri. Fu rem if gi kipaluc ebekup sobcule ahpe upasel moef degcik aco fuwfed hu an nonuca idjesdob. Eshipmu capvosuf puvof bumunniv fezuevi gapelgo jacop gepha tofpo rin pucori mifo wih latir jezkic."
  },
  "apiKey": "92d2366ec593426d821200ea7f05d9f1c994807207959a9f0eaf805fc6f9cf52",
  "currency": {
    "code": "CZK",
    "name": "Czech Republic Koruna"
  }
}